CHANGES.txt
DEPENDENCES.txt
README.txt
setup.py
src/ng/__init__.py
src/ng.content.comment.egg-info/PKG-INFO
src/ng.content.comment.egg-info/SOURCES.txt
src/ng.content.comment.egg-info/dependency_links.txt
src/ng.content.comment.egg-info/namespace_packages.txt
src/ng.content.comment.egg-info/not-zip-safe
src/ng.content.comment.egg-info/requires.txt
src/ng.content.comment.egg-info/top_level.txt
src/ng/content/__init__.py
src/ng/content/comment/__init__.py
src/ng/content/comment/comment.py
src/ng/content/comment/commentannotation.py
src/ng/content/comment/commentannotationableadapter.py
src/ng/content/comment/configure.zcml
src/ng/content/comment/interfaces.py
src/ng/content/comment/ng.content.comment.txt
src/ng/content/comment/browser/__init__.py
src/ng/content/comment/browser/configure.zcml
src/ng/content/comment/etc/ng.content.comment-configure.zcml
